[
	{
		"type": "Animationspec",
		"name": "chest loot",
		"animation": "chest1-opening",
		"channel": 1,
		"permanent": true,
		"repeat_start": 10
	},
	{
		"type": "Animationspec",
		"name": "chest looted",
		"animation": "chest1-opening",
		"channel": 1,
		"permanent": true,
		"repeat_start": 10,
		"time": 10
	},
	{
		"type": "AnimationProfileSpec",
		"name": "chest",
		"animations":
		{
			"loot": "chest loot",
			"looted": "chest looted"
		}
	},
	{
		"type": "CraftingRecipeSpec",
		"name": "chest",
		"effect": "craftwood1",
		"materials": {"log": 10},
		"modes": {"wood": true}
	},
	{
		"type": "Itemspec",
		"name": "chest",
		"categories": {"container": true, "generate": true},
		"animations": {"default": "chest"},
		"model": "chest1",
		"icon": "chest1",
		"mass": 30,
		"important": true,
		"inventory_size": 8,
		"inventory_type": "chest",
		"loot_categories": ["armor", "book", "material", "misc", "potion", "shield", "weapon"],
		"loot_count_min": 2,
		"loot_count_max": 4,
		"stacking": false,
		"usages": {"loot": true}
	},
	{
		"type": "Itemspec",
		"name": "treasure chest",
		"categories": {"container": true},
		"animations": {"default": "chest"},
		"icon": "chest1",
		"mass": 30,
		"model": "chest1",
		"important": true,
		"inventory_size": 8,
		"inventory_type": "chest",
		"loot_categories": ["armor", "shield", "weapon"],
		"loot_count_min": 8,
		"loot_count_max": 8,
		"stacking": false,
		"usages": {"loot": true}
	}
]
